{"variavel":{"desc":"Área da unidade territorial","unid":"km²"},"municipios":{"310010":{"n":"Abadia dos Dourados", "v":"881.064", "m":"881,064", "f":3},"310020":{"n":"Abaeté", "v":"1817.067", "m":"1.817,067", "f":3},"310030":{"n":"Abre Campo", "v":"470.551", "m":"470,551", "f":2},"310040":{"n":"Acaiaca", "v":"101.886", "m":"101,886", "f":0},"310050":{"n":"Açucena", "v":"815.422", "m":"815,422", "f":3},"310060":{"n":"Água Boa", "v":"1320.268", "m":"1.320,268", "f":3},"310070":{"n":"Água Comprida", "v":"492.215", "m":"492,215", "f":2},"310080":{"n":"Aguanil", "v":"232.091", "m":"232,091", "f":1},"310090":{"n":"Águas Formosas", "v":"820.079", "m":"820,079", "f":3},"310100":{"n":"Águas Vermelhas", "v":"1259.288", "m":"1.259,288", "f":3},"310110":{"n":"Aimorés", "v":"1348.775", "m":"1.348,775", "f":3},"310120":{"n":"Aiuruoca", "v":"649.68", "m":"649,680", "f":2},"310130":{"n":"Alagoa", "v":"161.356", "m":"161,356", "f":0},"310140":{"n":"Albertina", "v":"58.01", "m":"58,010", "f":0},"310150":{"n":"Além Paraíba", "v":"510.25", "m":"510,250", "f":2},"310160":{"n":"Alfenas", "v":"850.446", "m":"850,446", "f":3},"310163":{"n":"Alfredo Vasconcelos", "v":"130.815", "m":"130,815", "f":0},"310170":{"n":"Almenara", "v":"2294.426", "m":"2.294,426", "f":3},"310180":{"n":"Alpercata", "v":"166.972", "m":"166,972", "f":0},"310190":{"n":"Alpinópolis", "v":"454.751", "m":"454,751", "f":2},"310200":{"n":"Alterosa", "v":"362.01", "m":"362,010", "f":1},"310205":{"n":"Alto Caparaó", "v":"103.69", "m":"103,690", "f":0},"310210":{"n":"Alto Rio Doce", "v":"518.053", "m":"518,053", "f":2},"310220":{"n":"Alvarenga", "v":"278.173", "m":"278,173", "f":1},"310230":{"n":"Alvinópolis", "v":"599.443", "m":"599,443", "f":2},"310240":{"n":"Alvorada de Minas", "v":"374.008", "m":"374,008", "f":2},"310250":{"n":"Amparo do Serra", "v":"136.186", "m":"136,186", "f":0},"310260":{"n":"Andradas", "v":"469.368", "m":"469,368", "f":2},"310270":{"n":"Cachoeira de Pajeú", "v":"695.672", "m":"695,672", "f":2},"310280":{"n":"Andrelândia", "v":"1005.285", "m":"1.005,285", "f":3},"310285":{"n":"Angelândia", "v":"185.211", "m":"185,211", "f":0},"310290":{"n":"Antônio Carlos", "v":"529.915", "m":"529,915", "f":2},"310300":{"n":"Antônio Dias", "v":"787.061", "m":"787,061", "f":3},"310310":{"n":"Antônio Prado de Minas", "v":"83.802", "m":"83,802", "f":0},"310320":{"n":"Araçaí", "v":"186.543", "m":"186,543", "f":0},"310330":{"n":"Aracitaba", "v":"106.608", "m":"106,608", "f":0},"310340":{"n":"Araçuaí", "v":"2236.279", "m":"2.236,279", "f":3},"310350":{"n":"Araguari", "v":"2729.508", "m":"2.729,508", "f":3},"310360":{"n":"Arantina", "v":"89.42", "m":"89,420", "f":0},"310370":{"n":"Araponga", "v":"303.793", "m":"303,793", "f":1},"310375":{"n":"Araporã", "v":"295.837", "m":"295,837", "f":1},"310380":{"n":"Arapuá", "v":"173.894", "m":"173,894", "f":0},"310390":{"n":"Araújos", "v":"245.522", "m":"245,522", "f":1},"310400":{"n":"Araxá", "v":"1164.358", "m":"1.164,358", "f":3},"310410":{"n":"Arceburgo", "v":"162.875", "m":"162,875", "f":0},"310420":{"n":"Arcos", "v":"509.873", "m":"509,873", "f":2},"310430":{"n":"Areado", "v":"283.124", "m":"283,124", "f":1},"310440":{"n":"Argirita", "v":"159.378", "m":"159,378", "f":0},"310445":{"n":"Aricanduva", "v":"243.329", "m":"243,329", "f":1},"310450":{"n":"Arinos", "v":"5279.419", "m":"5.279,419", "f":3},"310460":{"n":"Astolfo Dutra", "v":"158.891", "m":"158,891", "f":0},"310470":{"n":"Ataléia", "v":"1836.977", "m":"1.836,977", "f":3},"310480":{"n":"Augusto de Lima", "v":"1254.832", "m":"1.254,832", "f":3},"310490":{"n":"Baependi", "v":"750.554", "m":"750,554", "f":3},"310500":{"n":"Baldim", "v":"556.266", "m":"556,266", "f":2},"310510":{"n":"Bambuí", "v":"1455.819", "m":"1.455,819", "f":3},"310520":{"n":"Bandeira", "v":"483.789", "m":"483,789", "f":2},"310530":{"n":"Bandeira do Sul", "v":"47.266", "m":"47,266", "f":0},"310540":{"n":"Barão de Cocais", "v":"340.585", "m":"340,585", "f":1},"310550":{"n":"Barão de Monte Alto", "v":"198.313", "m":"198,313", "f":1},"310560":{"n":"Barbacena", "v":"759.186", "m":"759,186", "f":3},"310570":{"n":"Barra Longa", "v":"383.628", "m":"383,628", "f":2},"310590":{"n":"Barroso", "v":"82.07", "m":"82,070", "f":0},"310600":{"n":"Bela Vista de Minas", "v":"109.143", "m":"109,143", "f":0},"310610":{"n":"Belmiro Braga", "v":"393.13", "m":"393,130", "f":2},"310620":{"n":"Belo Horizonte", "v":"331.401", "m":"331,401", "f":1},"310630":{"n":"Belo Oriente", "v":"334.909", "m":"334,909", "f":1},"310640":{"n":"Belo Vale", "v":"365.923", "m":"365,923", "f":2},"310650":{"n":"Berilo", "v":"587.106", "m":"587,106", "f":2},"310660":{"n":"Bertópolis", "v":"427.803", "m":"427,803", "f":2},"310665":{"n":"Berizal", "v":"488.756", "m":"488,756", "f":2},"310670":{"n":"Betim", "v":"343.736", "m":"343,736", "f":1},"310680":{"n":"Bias Fortes", "v":"283.535", "m":"283,535", "f":1},"310690":{"n":"Bicas", "v":"140.082", "m":"140,082", "f":0},"310700":{"n":"Biquinhas", "v":"458.948", "m":"458,948", "f":2},"310710":{"n":"Boa Esperança", "v":"860.669", "m":"860,669", "f":3},"310720":{"n":"Bocaina de Minas", "v":"504.974", "m":"504,974", "f":2},"310730":{"n":"Bocaiúva", "v":"3227.627", "m":"3.227,627", "f":3},"310740":{"n":"Bom Despacho", "v":"1213.546", "m":"1.213,546", "f":3},"310750":{"n":"Bom Jardim de Minas", "v":"412.021", "m":"412,021", "f":2},"310760":{"n":"Bom Jesus da Penha", "v":"208.349", "m":"208,349", "f":1},"310770":{"n":"Bom Jesus do Amparo", "v":"195.611", "m":"195,611", "f":0},"310780":{"n":"Bom Jesus do Galho", "v":"592.289", "m":"592,289", "f":2},"310790":{"n":"Bom Repouso", "v":"229.845", "m":"229,845", "f":1},"310800":{"n":"Bom Sucesso", "v":"705.046", "m":"705,046", "f":2},"310810":{"n":"Bonfim", "v":"301.865", "m":"301,865", "f":1},"310820":{"n":"Bonfinópolis de Minas", "v":"1850.487", "m":"1.850,487", "f":3},"310825":{"n":"Bonito de Minas", "v":"3904.911", "m":"3.904,911", "f":3},"310830":{"n":"Borda da Mata", "v":"301.108", "m":"301,108", "f":1},"310840":{"n":"Botelhos", "v":"334.089", "m":"334,089", "f":1},"310850":{"n":"Botumirim", "v":"1568.884", "m":"1.568,884", "f":3},"310855":{"n":"Brasilândia de Minas", "v":"2509.694", "m":"2.509,694", "f":3},"310860":{"n":"Brasília de Minas", "v":"1399.484", "m":"1.399,484", "f":3},"310870":{"n":"Brás Pires", "v":"223.351", "m":"223,351", "f":1},"310880":{"n":"Braúnas", "v":"378.318", "m":"378,318", "f":2},"310890":{"n":"Brazópolis", "v":"367.688", "m":"367,688", "f":2},"310900":{"n":"Brumadinho", "v":"639.434", "m":"639,434", "f":2},"310910":{"n":"Bueno Brandão", "v":"356.15", "m":"356,150", "f":1},"310920":{"n":"Buenópolis", "v":"1599.881", "m":"1.599,881", "f":3},"310925":{"n":"Bugre", "v":"161.906", "m":"161,906", "f":0},"310930":{"n":"Buritis", "v":"5225.186", "m":"5.225,186", "f":3},"310940":{"n":"Buritizeiro", "v":"7218.401", "m":"7.218,401", "f":3},"310945":{"n":"Cabeceira Grande", "v":"1031.409", "m":"1.031,409", "f":3},"310950":{"n":"Cabo Verde", "v":"368.206", "m":"368,206", "f":2},"310960":{"n":"Cachoeira da Prata", "v":"61.381", "m":"61,381", "f":0},"310970":{"n":"Cachoeira de Minas", "v":"304.243", "m":"304,243", "f":1},"310980":{"n":"Cachoeira Dourada", "v":"200.928", "m":"200,928", "f":1},"310990":{"n":"Caetanópolis", "v":"156.039", "m":"156,039", "f":0},"311000":{"n":"Caeté", "v":"542.571", "m":"542,571", "f":2},"311010":{"n":"Caiana", "v":"106.459", "m":"106,459", "f":0},"311020":{"n":"Cajuri", "v":"83.038", "m":"83,038", "f":0},"311030":{"n":"Caldas", "v":"711.414", "m":"711,414", "f":2},"311040":{"n":"Camacho", "v":"223.001", "m":"223,001", "f":1},"311050":{"n":"Camanducaia", "v":"528.688", "m":"528,688", "f":2},"311060":{"n":"Cambuí", "v":"244.567", "m":"244,567", "f":1},"311070":{"n":"Cambuquira", "v":"246.38", "m":"246,380", "f":1},"311080":{"n":"Campanário", "v":"442.398", "m":"442,398", "f":2},"311090":{"n":"Campanha", "v":"335.587", "m":"335,587", "f":1},"311100":{"n":"Campestre", "v":"577.843", "m":"577,843", "f":2},"311110":{"n":"Campina Verde", "v":"3650.749", "m":"3.650,749", "f":3},"311115":{"n":"Campo Azul", "v":"505.914", "m":"505,914", "f":2},"311120":{"n":"Campo Belo", "v":"528.225", "m":"528,225", "f":2},"311130":{"n":"Campo do Meio", "v":"275.426", "m":"275,426", "f":1},"311140":{"n":"Campo Florido", "v":"1264.245", "m":"1.264,245", "f":3},"311150":{"n":"Campos Altos", "v":"710.645", "m":"710,645", "f":2},"311160":{"n":"Campos Gerais", "v":"769.504", "m":"769,504", "f":3},"311170":{"n":"Canaã", "v":"174.9", "m":"174,900", "f":0},"311180":{"n":"Canápolis", "v":"839.737", "m":"839,737", "f":3},"311190":{"n":"Cana Verde", "v":"212.721", "m":"212,721", "f":1},"311200":{"n":"Candeias", "v":"720.512", "m":"720,512", "f":2},"311205":{"n":"Cantagalo", "v":"141.855", "m":"141,855", "f":0},"311210":{"n":"Caparaó", "v":"130.694", "m":"130,694", "f":0},"311220":{"n":"Capela Nova", "v":"111.073", "m":"111,073", "f":0},"311230":{"n":"Capelinha", "v":"965.368", "m":"965,368", "f":3},"311240":{"n":"Capetinga", "v":"297.937", "m":"297,937", "f":1},"311250":{"n":"Capim Branco", "v":"95.333", "m":"95,333", "f":0},"311260":{"n":"Capinópolis", "v":"620.716", "m":"620,716", "f":2},"311265":{"n":"Capitão Andrade", "v":"279.088", "m":"279,088", "f":1},"311270":{"n":"Capitão Enéas", "v":"971.583", "m":"971,583", "f":3},"311280":{"n":"Capitólio", "v":"521.802", "m":"521,802", "f":2},"311290":{"n":"Caputira", "v":"187.704", "m":"187,704", "f":0},"311300":{"n":"Caraí", "v":"1242.2", "m":"1.242,200", "f":3},"311310":{"n":"Caranaíba", "v":"159.95", "m":"159,950", "f":0},"311320":{"n":"Carandaí", "v":"487.28", "m":"487,280", "f":2},"311330":{"n":"Carangola", "v":"353.404", "m":"353,404", "f":1},"311340":{"n":"Caratinga", "v":"1258.778", "m":"1.258,778", "f":3},"311350":{"n":"Carbonita", "v":"1456.095", "m":"1.456,095", "f":3},"311360":{"n":"Careaçu", "v":"181.009", "m":"181,009", "f":0},"311370":{"n":"Carlos Chagas", "v":"3202.984", "m":"3.202,984", "f":3},"311380":{"n":"Carmésia", "v":"259.103", "m":"259,103", "f":1},"311390":{"n":"Carmo da Cachoeira", "v":"506.333", "m":"506,333", "f":2},"311400":{"n":"Carmo da Mata", "v":"357.178", "m":"357,178", "f":1},"311410":{"n":"Carmo de Minas", "v":"322.285", "m":"322,285", "f":1},"311420":{"n":"Carmo do Cajuru", "v":"455.808", "m":"455,808", "f":2},"311430":{"n":"Carmo do Paranaíba", "v":"1307.862", "m":"1.307,862", "f":3},"311440":{"n":"Carmo do Rio Claro", "v":"1065.685", "m":"1.065,685", "f":3},"311450":{"n":"Carmópolis de Minas", "v":"400.01", "m":"400,010", "f":2},"311455":{"n":"Carneirinho", "v":"2063.315", "m":"2.063,315", "f":3},"311460":{"n":"Carrancas", "v":"727.894", "m":"727,894", "f":2},"311470":{"n":"Carvalhópolis", "v":"81.101", "m":"81,101", "f":0},"311480":{"n":"Carvalhos", "v":"282.254", "m":"282,254", "f":1},"311490":{"n":"Casa Grande", "v":"157.727", "m":"157,727", "f":0},"311500":{"n":"Cascalho Rico", "v":"367.308", "m":"367,308", "f":2},"311510":{"n":"Cássia", "v":"665.802", "m":"665,802", "f":2},"311520":{"n":"Conceição da Barra de Minas", "v":"273.014", "m":"273,014", "f":1},"311530":{"n":"Cataguases", "v":"491.767", "m":"491,767", "f":2},"311535":{"n":"Catas Altas", "v":"240.042", "m":"240,042", "f":1},"311540":{"n":"Catas Altas da Noruega", "v":"141.622", "m":"141,622", "f":0},"311545":{"n":"Catuji", "v":"419.526", "m":"419,526", "f":2},"311547":{"n":"Catuti", "v":"287.812", "m":"287,812", "f":1},"311550":{"n":"Caxambu", "v":"100.483", "m":"100,483", "f":0},"311560":{"n":"Cedro do Abaeté", "v":"283.211", "m":"283,211", "f":1},"311570":{"n":"Central de Minas", "v":"204.328", "m":"204,328", "f":1},"311580":{"n":"Centralina", "v":"327.191", "m":"327,191", "f":1},"311590":{"n":"Chácara", "v":"152.807", "m":"152,807", "f":0},"311600":{"n":"Chalé", "v":"212.674", "m":"212,674", "f":1},"311610":{"n":"Chapada do Norte", "v":"830.969", "m":"830,969", "f":3},"311615":{"n":"Chapada Gaúcha", "v":"3255.187", "m":"3.255,187", "f":3},"311620":{"n":"Chiador", "v":"252.852", "m":"252,852", "f":1},"311630":{"n":"Cipotânea", "v":"153.479", "m":"153,479", "f":0},"311640":{"n":"Claraval", "v":"227.627", "m":"227,627", "f":1},"311650":{"n":"Claro dos Poções", "v":"720.424", "m":"720,424", "f":2},"311660":{"n":"Cláudio", "v":"630.706", "m":"630,706", "f":2},"311670":{"n":"Coimbra", "v":"106.875", "m":"106,875", "f":0},"311680":{"n":"Coluna", "v":"348.492", "m":"348,492", "f":1},"311690":{"n":"Comendador Gomes", "v":"1041.047", "m":"1.041,047", "f":3},"311700":{"n":"Comercinho", "v":"654.961", "m":"654,961", "f":2},"311710":{"n":"Conceição da Aparecida", "v":"352.521", "m":"352,521", "f":1},"311720":{"n":"Conceição das Pedras", "v":"102.206", "m":"102,206", "f":0},"311730":{"n":"Conceição das Alagoas", "v":"1340.25", "m":"1.340,250", "f":3},"311740":{"n":"Conceição de Ipanema", "v":"253.935", "m":"253,935", "f":1},"311750":{"n":"Conceição do Mato Dentro", "v":"1726.83", "m":"1.726,830", "f":3},"311760":{"n":"Conceição do Pará", "v":"250.331", "m":"250,331", "f":1},"311770":{"n":"Conceição do Rio Verde", "v":"369.681", "m":"369,681", "f":2},"311780":{"n":"Conceição dos Ouros", "v":"180.191", "m":"180,191", "f":0},"311783":{"n":"Cônego Marinho", "v":"1641.998", "m":"1.641,998", "f":3},"311787":{"n":"Confins", "v":"42.355", "m":"42,355", "f":0},"311790":{"n":"Congonhal", "v":"205.125", "m":"205,125", "f":1},"311800":{"n":"Congonhas", "v":"304.067", "m":"304,067", "f":1},"311810":{"n":"Congonhas do Norte", "v":"398.851", "m":"398,851", "f":2},"311820":{"n":"Conquista", "v":"618.363", "m":"618,363", "f":2},"311830":{"n":"Conselheiro Lafaiete", "v":"370.246", "m":"370,246", "f":2},"311840":{"n":"Conselheiro Pena", "v":"1483.884", "m":"1.483,884", "f":3},"311850":{"n":"Consolação", "v":"89.122", "m":"89,122", "f":0},"311860":{"n":"Contagem", "v":"195.268", "m":"195,268", "f":0},"311870":{"n":"Coqueiral", "v":"296.163", "m":"296,163", "f":1},"311880":{"n":"Coração de Jesus", "v":"2225.216", "m":"2.225,216", "f":3},"311890":{"n":"Cordisburgo", "v":"823.654", "m":"823,654", "f":3},"311900":{"n":"Cordislândia", "v":"179.543", "m":"179,543", "f":0},"311910":{"n":"Corinto", "v":"2525.397", "m":"2.525,397", "f":3},"311920":{"n":"Coroaci", "v":"576.274", "m":"576,274", "f":2},"311930":{"n":"Coromandel", "v":"3313.116", "m":"3.313,116", "f":3},"311940":{"n":"Coronel Fabriciano", "v":"221.252", "m":"221,252", "f":1},"311950":{"n":"Coronel Murta", "v":"815.413", "m":"815,413", "f":3},"311960":{"n":"Coronel Pacheco", "v":"131.511", "m":"131,511", "f":0},"311970":{"n":"Coronel Xavier Chaves", "v":"140.954", "m":"140,954", "f":0},"311980":{"n":"Córrego Danta", "v":"657.425", "m":"657,425", "f":2},"311990":{"n":"Córrego do Bom Jesus", "v":"123.651", "m":"123,651", "f":0},"311995":{"n":"Córrego Fundo", "v":"101.112", "m":"101,112", "f":0},"312000":{"n":"Córrego Novo", "v":"205.385", "m":"205,385", "f":1},"312010":{"n":"Couto de Magalhães de Minas", "v":"485.654", "m":"485,654", "f":2},"312015":{"n":"Crisólita", "v":"966.202", "m":"966,202", "f":3},"312020":{"n":"Cristais", "v":"628.434", "m":"628,434", "f":2},"312030":{"n":"Cristália", "v":"840.702", "m":"840,702", "f":3},"312040":{"n":"Cristiano Otoni", "v":"132.872", "m":"132,872", "f":0},"312050":{"n":"Cristina", "v":"311.33", "m":"311,330", "f":1},"312060":{"n":"Crucilândia", "v":"167.164", "m":"167,164", "f":0},"312070":{"n":"Cruzeiro da Fortaleza", "v":"188.131", "m":"188,131", "f":0},"312080":{"n":"Cruzília", "v":"522.419", "m":"522,419", "f":2},"312083":{"n":"Cuparaque", "v":"226.75", "m":"226,750", "f":1},"312087":{"n":"Curral de Dentro", "v":"568.263", "m":"568,263", "f":2},"312090":{"n":"Curvelo", "v":"3296.2", "m":"3.296,200", "f":3},"312100":{"n":"Datas", "v":"310.099", "m":"310,099", "f":1},"312110":{"n":"Delfim Moreira", "v":"408.473", "m":"408,473", "f":2},"312120":{"n":"Delfinópolis", "v":"1378.423", "m":"1.378,423", "f":3},"312125":{"n":"Delta", "v":"102.84", "m":"102,840", "f":0},"312130":{"n":"Descoberto", "v":"213.168", "m":"213,168", "f":1},"312140":{"n":"Desterro de Entre Rios", "v":"377.165", "m":"377,165", "f":2},"312150":{"n":"Desterro do Melo", "v":"142.279", "m":"142,279", "f":0},"312160":{"n":"Diamantina", "v":"3891.659", "m":"3.891,659", "f":3},"312170":{"n":"Diogo de Vasconcelos", "v":"165.091", "m":"165,091", "f":0},"312180":{"n":"Dionísio", "v":"344.442", "m":"344,442", "f":1},"312190":{"n":"Divinésia", "v":"116.97", "m":"116,970", "f":0},"312200":{"n":"Divino", "v":"337.776", "m":"337,776", "f":1},"312210":{"n":"Divino das Laranjeiras", "v":"342.249", "m":"342,249", "f":1},"312220":{"n":"Divinolândia de Minas", "v":"133.12", "m":"133,120", "f":0},"312230":{"n":"Divinópolis", "v":"708.115", "m":"708,115", "f":2},"312235":{"n":"Divisa Alegre", "v":"117.809", "m":"117,809", "f":0},"312240":{"n":"Divisa Nova", "v":"216.955", "m":"216,955", "f":1},"312245":{"n":"Divisópolis", "v":"572.926", "m":"572,926", "f":2},"312247":{"n":"Dom Bosco", "v":"817.383", "m":"817,383", "f":3},"312250":{"n":"Dom Cavati", "v":"59.52", "m":"59,520", "f":0},"312260":{"n":"Dom Joaquim", "v":"398.822", "m":"398,822", "f":2},"312270":{"n":"Dom Silvério", "v":"194.972", "m":"194,972", "f":0},"312280":{"n":"Dom Viçoso", "v":"113.921", "m":"113,921", "f":0},"312290":{"n":"Dona Eusébia", "v":"70.231", "m":"70,231", "f":0},"312300":{"n":"Dores de Campos", "v":"124.842", "m":"124,842", "f":0},"312310":{"n":"Dores de Guanhães", "v":"382.124", "m":"382,124", "f":2},"312320":{"n":"Dores do Indaiá", "v":"1111.202", "m":"1.111,202", "f":3},"312330":{"n":"Dores do Turvo", "v":"231.169", "m":"231,169", "f":1},"312340":{"n":"Doresópolis", "v":"152.912", "m":"152,912", "f":0},"312350":{"n":"Douradoquara", "v":"312.878", "m":"312,878", "f":1},"312352":{"n":"Durandé", "v":"217.461", "m":"217,461", "f":1},"312360":{"n":"Elói Mendes", "v":"499.537", "m":"499,537", "f":2},"312370":{"n":"Engenheiro Caldas", "v":"187.058", "m":"187,058", "f":0},"312380":{"n":"Engenheiro Navarro", "v":"608.306", "m":"608,306", "f":2},"312385":{"n":"Entre Folhas", "v":"85.209", "m":"85,209", "f":0},"312390":{"n":"Entre Rios de Minas", "v":"456.796", "m":"456,796", "f":2},"312400":{"n":"Ervália", "v":"357.489", "m":"357,489", "f":1},"312410":{"n":"Esmeraldas", "v":"909.488", "m":"909,488", "f":3},"312420":{"n":"Espera Feliz", "v":"317.638", "m":"317,638", "f":1},"312430":{"n":"Espinosa", "v":"1868.97", "m":"1.868,970", "f":3},"312440":{"n":"Espírito Santo do Dourado", "v":"263.879", "m":"263,879", "f":1},"312450":{"n":"Estiva", "v":"243.872", "m":"243,872", "f":1},"312460":{"n":"Estrela Dalva", "v":"131.365", "m":"131,365", "f":0},"312470":{"n":"Estrela do Indaiá", "v":"635.981", "m":"635,981", "f":2},"312480":{"n":"Estrela do Sul", "v":"822.454", "m":"822,454", "f":3},"312490":{"n":"Eugenópolis", "v":"309.395", "m":"309,395", "f":1},"312500":{"n":"Ewbank da Câmara", "v":"103.834", "m":"103,834", "f":0},"312510":{"n":"Extrema", "v":"244.585", "m":"244,585", "f":1},"312520":{"n":"Fama", "v":"86.024", "m":"86,024", "f":0},"312530":{"n":"Faria Lemos", "v":"165.224", "m":"165,224", "f":0},"312540":{"n":"Felício dos Santos", "v":"357.622", "m":"357,622", "f":1},"312550":{"n":"São Gonçalo do Rio Preto", "v":"314.458", "m":"314,458", "f":1},"312560":{"n":"Felisburgo", "v":"596.215", "m":"596,215", "f":2},"312570":{"n":"Felixlândia", "v":"1554.627", "m":"1.554,627", "f":3},"312580":{"n":"Fernandes Tourinho", "v":"151.875", "m":"151,875", "f":0},"312590":{"n":"Ferros", "v":"1088.795", "m":"1.088,795", "f":3},"312595":{"n":"Fervedouro", "v":"357.683", "m":"357,683", "f":1},"312600":{"n":"Florestal", "v":"194.21", "m":"194,210", "f":0},"312610":{"n":"Formiga", "v":"1501.915", "m":"1.501,915", "f":3},"312620":{"n":"Formoso", "v":"3685.702", "m":"3.685,702", "f":3},"312630":{"n":"Fortaleza de Minas", "v":"218.792", "m":"218,792", "f":1},"312640":{"n":"Fortuna de Minas", "v":"198.709", "m":"198,709", "f":1},"312650":{"n":"Francisco Badaró", "v":"461.345", "m":"461,345", "f":2},"312660":{"n":"Francisco Dumont", "v":"1576.128", "m":"1.576,128", "f":3},"312670":{"n":"Francisco Sá", "v":"2747.288", "m":"2.747,288", "f":3},"312675":{"n":"Franciscópolis", "v":"717.087", "m":"717,087", "f":2},"312680":{"n":"Frei Gaspar", "v":"626.672", "m":"626,672", "f":2},"312690":{"n":"Frei Inocêncio", "v":"469.557", "m":"469,557", "f":2},"312695":{"n":"Frei Lagonegro", "v":"167.474", "m":"167,474", "f":0},"312700":{"n":"Fronteira", "v":"199.987", "m":"199,987", "f":1},"312705":{"n":"Fronteira dos Vales", "v":"320.757", "m":"320,757", "f":1},"312707":{"n":"Fruta de Leite", "v":"762.785", "m":"762,785", "f":3},"312710":{"n":"Frutal", "v":"2426.965", "m":"2.426,965", "f":3},"312720":{"n":"Funilândia", "v":"199.797", "m":"199,797", "f":1},"312730":{"n":"Galiléia", "v":"720.355", "m":"720,355", "f":2},"312733":{"n":"Gameleiras", "v":"1733.203", "m":"1.733,203", "f":3},"312735":{"n":"Glaucilândia", "v":"145.861", "m":"145,861", "f":0},"312737":{"n":"Goiabeira", "v":"112.443", "m":"112,443", "f":0},"312738":{"n":"Goianá", "v":"152.039", "m":"152,039", "f":0},"312740":{"n":"Gonçalves", "v":"187.353", "m":"187,353", "f":0},"312750":{"n":"Gonzaga", "v":"209.348", "m":"209,348", "f":1},"312760":{"n":"Gouveia", "v":"866.601", "m":"866,601", "f":3},"312770":{"n":"Governador Valadares", "v":"2342.319", "m":"2.342,319", "f":3},"312780":{"n":"Grão Mogol", "v":"3885.294", "m":"3.885,294", "f":3},"312790":{"n":"Grupiara", "v":"193.141", "m":"193,141", "f":0},"312800":{"n":"Guanhães", "v":"1075.124", "m":"1.075,124", "f":3},"312810":{"n":"Guapé", "v":"934.345", "m":"934,345", "f":3},"312820":{"n":"Guaraciaba", "v":"348.596", "m":"348,596", "f":1},"312825":{"n":"Guaraciama", "v":"390.263", "m":"390,263", "f":2},"312830":{"n":"Guaranésia", "v":"294.828", "m":"294,828", "f":1},"312840":{"n":"Guarani", "v":"264.193", "m":"264,193", "f":1},"312850":{"n":"Guarará", "v":"88.655", "m":"88,655", "f":0},"312860":{"n":"Guarda-Mor", "v":"2069.79", "m":"2.069,790", "f":3},"312870":{"n":"Guaxupé", "v":"286.398", "m":"286,398", "f":1},"312880":{"n":"Guidoval", "v":"158.375", "m":"158,375", "f":0},"312890":{"n":"Guimarânia", "v":"366.833", "m":"366,833", "f":2},"312900":{"n":"Guiricema", "v":"293.578", "m":"293,578", "f":1},"312910":{"n":"Gurinhatã", "v":"1849.137", "m":"1.849,137", "f":3},"312920":{"n":"Heliodora", "v":"153.95", "m":"153,950", "f":0},"312930":{"n":"Iapu", "v":"340.579", "m":"340,579", "f":1},"312940":{"n":"Ibertioga", "v":"346.24", "m":"346,240", "f":1},"312950":{"n":"Ibiá", "v":"2704.132", "m":"2.704,132", "f":3},"312960":{"n":"Ibiaí", "v":"874.76", "m":"874,760", "f":3},"312965":{"n":"Ibiracatu", "v":"353.413", "m":"353,413", "f":1},"312970":{"n":"Ibiraci", "v":"562.095", "m":"562,095", "f":2},"312980":{"n":"Ibirité", "v":"72.573", "m":"72,573", "f":0},"312990":{"n":"Ibitiúra de Minas", "v":"68.316", "m":"68,316", "f":0},"313000":{"n":"Ibituruna", "v":"153.106", "m":"153,106", "f":0},"313005":{"n":"Icaraí de Minas", "v":"625.664", "m":"625,664", "f":2},"313010":{"n":"Igarapé", "v":"110.263", "m":"110,263", "f":0},"313020":{"n":"Igaratinga", "v":"218.343", "m":"218,343", "f":1},"313030":{"n":"Iguatama", "v":"628.2", "m":"628,200", "f":2},"313040":{"n":"Ijaci", "v":"105.246", "m":"105,246", "f":0},"313050":{"n":"Ilicínea", "v":"376.341", "m":"376,341", "f":2},"313055":{"n":"Imbé de Minas", "v":"196.735", "m":"196,735", "f":1},"313060":{"n":"Inconfidentes", "v":"149.611", "m":"149,611", "f":0},"313065":{"n":"Indaiabira", "v":"1004.149", "m":"1.004,149", "f":3},"313070":{"n":"Indianópolis", "v":"830.03", "m":"830,030", "f":3},"313080":{"n":"Ingaí", "v":"305.591", "m":"305,591", "f":1},"313090":{"n":"Inhapim", "v":"858.024", "m":"858,024", "f":3},"313100":{"n":"Inhaúma", "v":"244.996", "m":"244,996", "f":1},"313110":{"n":"Inimutaba", "v":"527.06", "m":"527,060", "f":2},"313115":{"n":"Ipaba", "v":"113.128", "m":"113,128", "f":0},"313120":{"n":"Ipanema", "v":"456.641", "m":"456,641", "f":2},"313130":{"n":"Ipatinga", "v":"164.884", "m":"164,884", "f":0},"313140":{"n":"Ipiaçu", "v":"466.02", "m":"466,020", "f":2},"313150":{"n":"Ipuiúna", "v":"298.195", "m":"298,195", "f":1},"313160":{"n":"Iraí de Minas", "v":"356.264", "m":"356,264", "f":1},"313170":{"n":"Itabira", "v":"1253.704", "m":"1.253,704", "f":3},"313180":{"n":"Itabirinha", "v":"208.982", "m":"208,982", "f":1},"313190":{"n":"Itabirito", "v":"542.609", "m":"542,609", "f":2},"313200":{"n":"Itacambira", "v":"1788.445", "m":"1.788,445", "f":3},"313210":{"n":"Itacarambi", "v":"1225.273", "m":"1.225,273", "f":3},"313220":{"n":"Itaguara", "v":"410.468", "m":"410,468", "f":2},"313230":{"n":"Itaipé", "v":"480.829", "m":"480,829", "f":2},"313240":{"n":"Itajubá", "v":"294.835", "m":"294,835", "f":1},"313250":{"n":"Itamarandiba", "v":"2735.573", "m":"2.735,573", "f":3},"313260":{"n":"Itamarati de Minas", "v":"94.568", "m":"94,568", "f":0},"313270":{"n":"Itambacuri", "v":"1419.209", "m":"1.419,209", "f":3},"313280":{"n":"Itambé do Mato Dentro", "v":"380.34", "m":"380,340", "f":2},"313290":{"n":"Itamogi", "v":"243.735", "m":"243,735", "f":1},"313300":{"n":"Itamonte", "v":"431.792", "m":"431,792", "f":2},"313310":{"n":"Itanhandu", "v":"143.363", "m":"143,363", "f":0},"313320":{"n":"Itanhomi", "v":"488.843", "m":"488,843", "f":2},"313330":{"n":"Itaobim", "v":"679.024", "m":"679,024", "f":2},"313340":{"n":"Itapagipe", "v":"1802.436", "m":"1.802,436", "f":3},"313350":{"n":"Itapecerica", "v":"1040.519", "m":"1.040,519", "f":3},"313360":{"n":"Itapeva", "v":"177.347", "m":"177,347", "f":0},"313370":{"n":"Itatiaiuçu", "v":"295.145", "m":"295,145", "f":1},"313375":{"n":"Itaú de Minas", "v":"153.421", "m":"153,421", "f":0},"313380":{"n":"Itaúna", "v":"495.769", "m":"495,769", "f":2},"313390":{"n":"Itaverava", "v":"284.22", "m":"284,220", "f":1},"313400":{"n":"Itinga", "v":"1649.622", "m":"1.649,622", "f":3},"313410":{"n":"Itueta", "v":"452.676", "m":"452,676", "f":2},"313420":{"n":"Ituiutaba", "v":"2598.046", "m":"2.598,046", "f":3},"313430":{"n":"Itumirim", "v":"234.802", "m":"234,802", "f":1},"313440":{"n":"Iturama", "v":"1404.663", "m":"1.404,663", "f":3},"313450":{"n":"Itutinga", "v":"372.018", "m":"372,018", "f":2},"313460":{"n":"Jaboticatubas", "v":"1114.972", "m":"1.114,972", "f":3},"313470":{"n":"Jacinto", "v":"1393.609", "m":"1.393,609", "f":3},"313480":{"n":"Jacuí", "v":"409.229", "m":"409,229", "f":2},"313490":{"n":"Jacutinga", "v":"347.75", "m":"347,750", "f":1},"313500":{"n":"Jaguaraçu", "v":"163.76", "m":"163,760", "f":0},"313505":{"n":"Jaíba", "v":"2626.331", "m":"2.626,331", "f":3},"313507":{"n":"Jampruca", "v":"517.095", "m":"517,095", "f":2},"313510":{"n":"Janaúba", "v":"2181.319", "m":"2.181,319", "f":3},"313520":{"n":"Januária", "v":"6661.666", "m":"6.661,666", "f":3},"313530":{"n":"Japaraíba", "v":"172.141", "m":"172,141", "f":0},"313535":{"n":"Japonvar", "v":"375.232", "m":"375,232", "f":2},"313540":{"n":"Jeceaba", "v":"236.25", "m":"236,250", "f":1},"313545":{"n":"Jenipapo de Minas", "v":"284.453", "m":"284,453", "f":1},"313550":{"n":"Jequeri", "v":"547.897", "m":"547,897", "f":2},"313560":{"n":"Jequitaí", "v":"1268.443", "m":"1.268,443", "f":3},"313570":{"n":"Jequitibá", "v":"445.03", "m":"445,030", "f":2},"313580":{"n":"Jequitinhonha", "v":"3514.216", "m":"3.514,216", "f":3},"313590":{"n":"Jesuânia", "v":"153.852", "m":"153,852", "f":0},"313600":{"n":"Joaíma", "v":"1664.19", "m":"1.664,190", "f":3},"313610":{"n":"Joanésia", "v":"233.292", "m":"233,292", "f":1},"313620":{"n":"João Monlevade", "v":"99.158", "m":"99,158", "f":0},"313630":{"n":"João Pinheiro", "v":"10727.471", "m":"10.727,471", "f":3},"313640":{"n":"Joaquim Felício", "v":"790.935", "m":"790,935", "f":3},"313650":{"n":"Jordânia", "v":"546.705", "m":"546,705", "f":2},"313652":{"n":"José Gonçalves de Minas", "v":"381.332", "m":"381,332", "f":2},"313655":{"n":"José Raydan", "v":"180.822", "m":"180,822", "f":0},"313657":{"n":"Josenópolis", "v":"541.393", "m":"541,393", "f":2},"313660":{"n":"Nova União", "v":"172.131", "m":"172,131", "f":0},"313665":{"n":"Juatuba", "v":"96.729", "m":"96,729", "f":0},"313670":{"n":"Juiz de Fora", "v":"1435.664", "m":"1.435,664", "f":3},"313680":{"n":"Juramento", "v":"431.63", "m":"431,630", "f":2},"313690":{"n":"Juruaia", "v":"220.353", "m":"220,353", "f":1},"313695":{"n":"Juvenília", "v":"1064.697", "m":"1.064,697", "f":3},"313700":{"n":"Ladainha", "v":"866.29", "m":"866,290", "f":3},"313710":{"n":"Lagamar", "v":"1474.562", "m":"1.474,562", "f":3},"313720":{"n":"Lagoa da Prata", "v":"439.984", "m":"439,984", "f":2},"313730":{"n":"Lagoa dos Patos", "v":"600.547", "m":"600,547", "f":2},"313740":{"n":"Lagoa Dourada", "v":"476.693", "m":"476,693", "f":2},"313750":{"n":"Lagoa Formosa", "v":"840.92", "m":"840,920", "f":3},"313753":{"n":"Lagoa Grande", "v":"1236.301", "m":"1.236,301", "f":3},"313760":{"n":"Lagoa Santa", "v":"229.267", "m":"229,267", "f":1},"313770":{"n":"Lajinha", "v":"431.921", "m":"431,921", "f":2},"313780":{"n":"Lambari", "v":"213.11", "m":"213,110", "f":1},"313790":{"n":"Lamim", "v":"118.602", "m":"118,602", "f":0},"313800":{"n":"Laranjal", "v":"204.882", "m":"204,882", "f":1},"313810":{"n":"Lassance", "v":"3204.217", "m":"3.204,217", "f":3},"313820":{"n":"Lavras", "v":"564.744", "m":"564,744", "f":2},"313830":{"n":"Leandro Ferreira", "v":"352.108", "m":"352,108", "f":1},"313835":{"n":"Leme do Prado", "v":"280.036", "m":"280,036", "f":1},"313840":{"n":"Leopoldina", "v":"943.076", "m":"943,076", "f":3},"313850":{"n":"Liberdade", "v":"401.337", "m":"401,337", "f":2},"313860":{"n":"Lima Duarte", "v":"848.564", "m":"848,564", "f":3},"313862":{"n":"Limeira do Oeste", "v":"1319.036", "m":"1.319,036", "f":3},"313865":{"n":"Lontra", "v":"258.874", "m":"258,874", "f":1},"313867":{"n":"Luisburgo", "v":"145.418", "m":"145,418", "f":0},"313868":{"n":"Luislândia", "v":"411.714", "m":"411,714", "f":2},"313870":{"n":"Luminárias", "v":"500.143", "m":"500,143", "f":2},"313880":{"n":"Luz", "v":"1171.659", "m":"1.171,659", "f":3},"313890":{"n":"Machacalis", "v":"332.378", "m":"332,378", "f":1},"313900":{"n":"Machado", "v":"585.958", "m":"585,958", "f":2},"313910":{"n":"Madre de Deus de Minas", "v":"492.909", "m":"492,909", "f":2},"313920":{"n":"Malacacheta", "v":"727.886", "m":"727,886", "f":2},"313925":{"n":"Mamonas", "v":"284.294", "m":"284,294", "f":1},"313930":{"n":"Manga", "v":"1950.184", "m":"1.950,184", "f":3},"313940":{"n":"Manhuaçu", "v":"628.318", "m":"628,318", "f":2},"313950":{"n":"Manhumirim", "v":"182.9", "m":"182,900", "f":0},"313960":{"n":"Mantena", "v":"685.208", "m":"685,208", "f":2},"313970":{"n":"Maravilhas", "v":"261.604", "m":"261,604", "f":1},"313980":{"n":"Mar de Espanha", "v":"371.6", "m":"371,600", "f":2},"313990":{"n":"Maria da Fé", "v":"202.898", "m":"202,898", "f":1},"314000":{"n":"Mariana", "v":"1194.208", "m":"1.194,208", "f":3},"314010":{"n":"Marilac", "v":"158.809", "m":"158,809", "f":0},"314015":{"n":"Mário Campos", "v":"35.196", "m":"35,196", "f":0},"314020":{"n":"Maripá de Minas", "v":"77.338", "m":"77,338", "f":0},"314030":{"n":"Marliéria", "v":"545.813", "m":"545,813", "f":2},"314040":{"n":"Marmelópolis", "v":"107.902", "m":"107,902", "f":0},"314050":{"n":"Martinho Campos", "v":"1058.418", "m":"1.058,418", "f":3},"314053":{"n":"Martins Soares", "v":"113.268", "m":"113,268", "f":0},"314055":{"n":"Mata Verde", "v":"227.539", "m":"227,539", "f":1},"314060":{"n":"Materlândia", "v":"280.53", "m":"280,530", "f":1},"314070":{"n":"Mateus Leme", "v":"302.714", "m":"302,714", "f":1},"314080":{"n":"Matias Barbosa", "v":"157.107", "m":"157,107", "f":0},"314085":{"n":"Matias Cardoso", "v":"1949.738", "m":"1.949,738", "f":3},"314090":{"n":"Matipó", "v":"266.99", "m":"266,990", "f":1},"314100":{"n":"Mato Verde", "v":"472.245", "m":"472,245", "f":2},"314110":{"n":"Matozinhos", "v":"252.28", "m":"252,280", "f":1},"314120":{"n":"Matutina", "v":"260.957", "m":"260,957", "f":1},"314130":{"n":"Medeiros", "v":"946.437", "m":"946,437", "f":3},"314140":{"n":"Medina", "v":"1435.903", "m":"1.435,903", "f":3},"314150":{"n":"Mendes Pimentel", "v":"305.507", "m":"305,507", "f":1},"314160":{"n":"Mercês", "v":"348.271", "m":"348,271", "f":1},"314170":{"n":"Mesquita", "v":"274.938", "m":"274,938", "f":1},"314180":{"n":"Minas Novas", "v":"1812.398", "m":"1.812,398", "f":3},"314190":{"n":"Minduri", "v":"219.774", "m":"219,774", "f":1},"314200":{"n":"Mirabela", "v":"723.278", "m":"723,278", "f":2},"314210":{"n":"Miradouro", "v":"301.672", "m":"301,672", "f":1},"314220":{"n":"Miraí", "v":"320.695", "m":"320,695", "f":1},"314225":{"n":"Miravânia", "v":"602.128", "m":"602,128", "f":2},"314230":{"n":"Moeda", "v":"155.112", "m":"155,112", "f":0},"314240":{"n":"Moema", "v":"202.705", "m":"202,705", "f":1},"314250":{"n":"Monjolos", "v":"650.911", "m":"650,911", "f":2},"314260":{"n":"Monsenhor Paulo", "v":"216.54", "m":"216,540", "f":1},"314270":{"n":"Montalvânia", "v":"1503.786", "m":"1.503,786", "f":3},"314280":{"n":"Monte Alegre de Minas", "v":"2595.957", "m":"2.595,957", "f":3},"314290":{"n":"Monte Azul", "v":"1001.296", "m":"1.001,296", "f":3},"314300":{"n":"Monte Belo", "v":"421.283", "m":"421,283", "f":2},"314310":{"n":"Monte Carmelo", "v":"1343.035", "m":"1.343,035", "f":3},"314315":{"n":"Monte Formoso", "v":"385.553", "m":"385,553", "f":2},"314320":{"n":"Monte Santo de Minas", "v":"594.632", "m":"594,632", "f":2},"314330":{"n":"Montes Claros", "v":"3568.941", "m":"3.568,941", "f":3},"314340":{"n":"Monte Sião", "v":"291.594", "m":"291,594", "f":1},"314345":{"n":"Montezuma", "v":"1130.419", "m":"1.130,419", "f":3},"314350":{"n":"Morada Nova de Minas", "v":"2084.275", "m":"2.084,275", "f":3},"314360":{"n":"Morro da Garça", "v":"414.772", "m":"414,772", "f":2},"314370":{"n":"Morro do Pilar", "v":"477.548", "m":"477,548", "f":2},"314380":{"n":"Munhoz", "v":"191.564", "m":"191,564", "f":0},"314390":{"n":"Muriaé", "v":"841.693", "m":"841,693", "f":3},"314400":{"n":"Mutum", "v":"1250.824", "m":"1.250,824", "f":3},"314410":{"n":"Muzambinho", "v":"409.948", "m":"409,948", "f":2},"314420":{"n":"Nacip Raydan", "v":"233.493", "m":"233,493", "f":1},"314430":{"n":"Nanuque", "v":"1517.941", "m":"1.517,941", "f":3},"314435":{"n":"Naque", "v":"127.173", "m":"127,173", "f":0},"314437":{"n":"Natalândia", "v":"468.66", "m":"468,660", "f":2},"314440":{"n":"Natércia", "v":"188.719", "m":"188,719", "f":0},"314450":{"n":"Nazareno", "v":"341.453", "m":"341,453", "f":1},"314460":{"n":"Nepomuceno", "v":"582.553", "m":"582,553", "f":2},"314465":{"n":"Ninheira", "v":"1108.255", "m":"1.108,255", "f":3},"314467":{"n":"Nova Belém", "v":"146.775", "m":"146,775", "f":0},"314470":{"n":"Nova Era", "v":"361.926", "m":"361,926", "f":1},"314480":{"n":"Nova Lima", "v":"429.004", "m":"429,004", "f":2},"314490":{"n":"Nova Módica", "v":"375.973", "m":"375,973", "f":2},"314500":{"n":"Nova Ponte", "v":"1111.011", "m":"1.111,011", "f":3},"314505":{"n":"Nova Porteirinha", "v":"120.943", "m":"120,943", "f":0},"314510":{"n":"Nova Resende", "v":"390.152", "m":"390,152", "f":2},"314520":{"n":"Nova Serrana", "v":"282.369", "m":"282,369", "f":1},"314530":{"n":"Novo Cruzeiro", "v":"1702.981", "m":"1.702,981", "f":3},"314535":{"n":"Novo Oriente de Minas", "v":"755.151", "m":"755,151", "f":3},"314537":{"n":"Novorizonte", "v":"271.61", "m":"271,610", "f":1},"314540":{"n":"Olaria", "v":"178.242", "m":"178,242", "f":0},"314545":{"n":"Olhos-d`Água", "v":"2092.078", "m":"2.092,078", "f":3},"314550":{"n":"Olímpio Noronha", "v":"54.633", "m":"54,633", "f":0},"314560":{"n":"Oliveira", "v":"897.294", "m":"897,294", "f":3},"314570":{"n":"Oliveira Fortes", "v":"111.13", "m":"111,130", "f":0},"314580":{"n":"Onça de Pitangui", "v":"246.976", "m":"246,976", "f":1},"314585":{"n":"Oratórios", "v":"89.068", "m":"89,068", "f":0},"314587":{"n":"Orizânia", "v":"121.8", "m":"121,800", "f":0},"314590":{"n":"Ouro Branco", "v":"258.726", "m":"258,726", "f":1},"314600":{"n":"Ouro Fino", "v":"533.658", "m":"533,658", "f":2},"314610":{"n":"Ouro Preto", "v":"1245.865", "m":"1.245,865", "f":3},"314620":{"n":"Ouro Verde de Minas", "v":"175.482", "m":"175,482", "f":0},"314625":{"n":"Padre Carvalho", "v":"446.326", "m":"446,326", "f":2},"314630":{"n":"Padre Paraíso", "v":"544.375", "m":"544,375", "f":2},"314640":{"n":"Paineiras", "v":"637.309", "m":"637,309", "f":2},"314650":{"n":"Pains", "v":"421.862", "m":"421,862", "f":2},"314655":{"n":"Pai Pedro", "v":"839.805", "m":"839,805", "f":3},"314660":{"n":"Paiva", "v":"58.419", "m":"58,419", "f":0},"314670":{"n":"Palma", "v":"316.476", "m":"316,476", "f":1},"314675":{"n":"Palmópolis", "v":"433.154", "m":"433,154", "f":2},"314690":{"n":"Papagaios", "v":"553.577", "m":"553,577", "f":2},"314700":{"n":"Paracatu", "v":"8229.592", "m":"8.229,592", "f":3},"314710":{"n":"Pará de Minas", "v":"551.247", "m":"551,247", "f":2},"314720":{"n":"Paraguaçu", "v":"424.296", "m":"424,296", "f":2},"314730":{"n":"Paraisópolis", "v":"331.238", "m":"331,238", "f":1},"314740":{"n":"Paraopeba", "v":"625.623", "m":"625,623", "f":2},"314750":{"n":"Passabém", "v":"94.183", "m":"94,183", "f":0},"314760":{"n":"Passa Quatro", "v":"277.221", "m":"277,221", "f":1},"314770":{"n":"Passa Tempo", "v":"429.172", "m":"429,172", "f":2},"314780":{"n":"Passa-Vinte", "v":"246.564", "m":"246,564", "f":1},"314790":{"n":"Passos", "v":"1338.07", "m":"1.338,070", "f":3},"314795":{"n":"Patis", "v":"444.196", "m":"444,196", "f":2},"314800":{"n":"Patos de Minas", "v":"3189.771", "m":"3.189,771", "f":3},"314810":{"n":"Patrocínio", "v":"2874.344", "m":"2.874,344", "f":3},"314820":{"n":"Patrocínio do Muriaé", "v":"108.245", "m":"108,245", "f":0},"314830":{"n":"Paula Cândido", "v":"268.321", "m":"268,321", "f":1},"314840":{"n":"Paulistas", "v":"220.564", "m":"220,564", "f":1},"314850":{"n":"Pavão", "v":"601.19", "m":"601,190", "f":2},"314860":{"n":"Peçanha", "v":"996.646", "m":"996,646", "f":3},"314870":{"n":"Pedra Azul", "v":"1594.651", "m":"1.594,651", "f":3},"314875":{"n":"Pedra Bonita", "v":"173.928", "m":"173,928", "f":0},"314880":{"n":"Pedra do Anta", "v":"173.168", "m":"173,168", "f":0},"314890":{"n":"Pedra do Indaiá", "v":"347.92", "m":"347,920", "f":1},"314900":{"n":"Pedra Dourada", "v":"69.99", "m":"69,990", "f":0},"314910":{"n":"Pedralva", "v":"217.99", "m":"217,990", "f":1},"314915":{"n":"Pedras de Maria da Cruz", "v":"1525.493", "m":"1.525,493", "f":3},"314920":{"n":"Pedrinópolis", "v":"357.891", "m":"357,891", "f":1},"314930":{"n":"Pedro Leopoldo", "v":"292.947", "m":"292,947", "f":1},"314940":{"n":"Pedro Teixeira", "v":"112.959", "m":"112,959", "f":0},"314950":{"n":"Pequeri", "v":"90.833", "m":"90,833", "f":0},"314960":{"n":"Pequi", "v":"203.991", "m":"203,991", "f":1},"314970":{"n":"Perdigão", "v":"249.322", "m":"249,322", "f":1},"314980":{"n":"Perdizes", "v":"2450.815", "m":"2.450,815", "f":3},"314990":{"n":"Perdões", "v":"270.657", "m":"270,657", "f":1},"314995":{"n":"Periquito", "v":"228.907", "m":"228,907", "f":1},"315000":{"n":"Pescador", "v":"317.463", "m":"317,463", "f":1},"315010":{"n":"Piau", "v":"192.196", "m":"192,196", "f":0},"315015":{"n":"Piedade de Caratinga", "v":"109.345", "m":"109,345", "f":0},"315020":{"n":"Piedade de Ponte Nova", "v":"83.733", "m":"83,733", "f":0},"315030":{"n":"Piedade do Rio Grande", "v":"322.814", "m":"322,814", "f":1},"315040":{"n":"Piedade dos Gerais", "v":"259.638", "m":"259,638", "f":1},"315050":{"n":"Pimenta", "v":"414.969", "m":"414,969", "f":2},"315053":{"n":"Pingo-d`Água", "v":"66.57", "m":"66,570", "f":0},"315057":{"n":"Pintópolis", "v":"1228.736", "m":"1.228,736", "f":3},"315060":{"n":"Piracema", "v":"280.335", "m":"280,335", "f":1},"315070":{"n":"Pirajuba", "v":"337.98", "m":"337,980", "f":1},"315080":{"n":"Piranga", "v":"658.812", "m":"658,812", "f":2},"315090":{"n":"Piranguçu", "v":"203.619", "m":"203,619", "f":1},"315100":{"n":"Piranguinho", "v":"124.803", "m":"124,803", "f":0},"315110":{"n":"Pirapetinga", "v":"190.681", "m":"190,681", "f":0},"315120":{"n":"Pirapora", "v":"549.514", "m":"549,514", "f":2},"315130":{"n":"Piraúba", "v":"144.289", "m":"144,289", "f":0},"315140":{"n":"Pitangui", "v":"569.611", "m":"569,611", "f":2},"315150":{"n":"Piumhi", "v":"902.468", "m":"902,468", "f":3},"315160":{"n":"Planura", "v":"317.52", "m":"317,520", "f":1},"315170":{"n":"Poço Fundo", "v":"474.244", "m":"474,244", "f":2},"315180":{"n":"Poços de Caldas", "v":"547.059", "m":"547,059", "f":2},"315190":{"n":"Pocrane", "v":"691.066", "m":"691,066", "f":2},"315200":{"n":"Pompéu", "v":"2551.074", "m":"2.551,074", "f":3},"315210":{"n":"Ponte Nova", "v":"470.643", "m":"470,643", "f":2},"315213":{"n":"Ponto Chique", "v":"602.799", "m":"602,799", "f":2},"315217":{"n":"Ponto dos Volantes", "v":"1212.413", "m":"1.212,413", "f":3},"315220":{"n":"Porteirinha", "v":"1749.683", "m":"1.749,683", "f":3},"315230":{"n":"Porto Firme", "v":"284.777", "m":"284,777", "f":1},"315240":{"n":"Poté", "v":"625.111", "m":"625,111", "f":2},"315250":{"n":"Pouso Alegre", "v":"543.068", "m":"543,068", "f":2},"315260":{"n":"Pouso Alto", "v":"263.034", "m":"263,034", "f":1},"315270":{"n":"Prados", "v":"264.115", "m":"264,115", "f":1},"315280":{"n":"Prata", "v":"4847.544", "m":"4.847,544", "f":3},"315290":{"n":"Pratápolis", "v":"215.516", "m":"215,516", "f":1},"315300":{"n":"Pratinha", "v":"622.478", "m":"622,478", "f":2},"315310":{"n":"Presidente Bernardes", "v":"236.798", "m":"236,798", "f":1},"315320":{"n":"Presidente Juscelino", "v":"695.882", "m":"695,882", "f":2},"315330":{"n":"Presidente Kubitschek", "v":"189.235", "m":"189,235", "f":0},"315340":{"n":"Presidente Olegário", "v":"3503.797", "m":"3.503,797", "f":3},"315350":{"n":"Alto Jequitibá", "v":"152.272", "m":"152,272", "f":0},"315360":{"n":"Prudente de Morais", "v":"124.189", "m":"124,189", "f":0},"315370":{"n":"Quartel Geral", "v":"556.436", "m":"556,436", "f":2},"315380":{"n":"Queluzito", "v":"153.56", "m":"153,560", "f":0},"315390":{"n":"Raposos", "v":"72.228", "m":"72,228", "f":0},"315400":{"n":"Raul Soares", "v":"763.364", "m":"763,364", "f":3},"315410":{"n":"Recreio", "v":"234.296", "m":"234,296", "f":1},"315415":{"n":"Reduto", "v":"151.859", "m":"151,859", "f":0},"315420":{"n":"Resende Costa", "v":"618.312", "m":"618,312", "f":2},"315430":{"n":"Resplendor", "v":"1081.796", "m":"1.081,796", "f":3},"315440":{"n":"Ressaquinha", "v":"183.016", "m":"183,016", "f":0},"315445":{"n":"Riachinho", "v":"1719.266", "m":"1.719,266", "f":3},"315450":{"n":"Riacho dos Machados", "v":"1315.54", "m":"1.315,540", "f":3},"315460":{"n":"Ribeirão das Neves", "v":"155.541", "m":"155,541", "f":0},"315470":{"n":"Ribeirão Vermelho", "v":"49.251", "m":"49,251", "f":0},"315480":{"n":"Rio Acima", "v":"229.812", "m":"229,812", "f":1},"315490":{"n":"Rio Casca", "v":"384.381", "m":"384,381", "f":2},"315500":{"n":"Rio Doce", "v":"112.094", "m":"112,094", "f":0},"315510":{"n":"Rio do Prado", "v":"479.815", "m":"479,815", "f":2},"315520":{"n":"Rio Espera", "v":"238.602", "m":"238,602", "f":1},"315530":{"n":"Rio Manso", "v":"231.54", "m":"231,540", "f":1},"315540":{"n":"Rio Novo", "v":"209.31", "m":"209,310", "f":1},"315550":{"n":"Rio Paranaíba", "v":"1352.353", "m":"1.352,353", "f":3},"315560":{"n":"Rio Pardo de Minas", "v":"3117.698", "m":"3.117,698", "f":3},"315570":{"n":"Rio Piracicaba", "v":"373.037", "m":"373,037", "f":2},"315580":{"n":"Rio Pomba", "v":"252.418", "m":"252,418", "f":1},"315590":{"n":"Rio Preto", "v":"348.046", "m":"348,046", "f":1},"315600":{"n":"Rio Vermelho", "v":"986.561", "m":"986,561", "f":3},"315610":{"n":"Ritápolis", "v":"404.805", "m":"404,805", "f":2},"315620":{"n":"Rochedo de Minas", "v":"79.402", "m":"79,402", "f":0},"315630":{"n":"Rodeiro", "v":"72.673", "m":"72,673", "f":0},"315640":{"n":"Romaria", "v":"407.557", "m":"407,557", "f":2},"315645":{"n":"Rosário da Limeira", "v":"111.156", "m":"111,156", "f":0},"315650":{"n":"Rubelita", "v":"1110.295", "m":"1.110,295", "f":3},"315660":{"n":"Rubim", "v":"965.174", "m":"965,174", "f":3},"315670":{"n":"Sabará", "v":"302.173", "m":"302,173", "f":1},"315680":{"n":"Sabinópolis", "v":"919.811", "m":"919,811", "f":3},"315690":{"n":"Sacramento", "v":"3073.268", "m":"3.073,268", "f":3},"315700":{"n":"Salinas", "v":"1861.653", "m":"1.861,653", "f":3},"315710":{"n":"Salto da Divisa", "v":"937.924", "m":"937,924", "f":3},"315720":{"n":"Santa Bárbara", "v":"684.06", "m":"684,060", "f":2},"315725":{"n":"Santa Bárbara do Leste", "v":"107.402", "m":"107,402", "f":0},"315727":{"n":"Santa Bárbara do Monte Verde", "v":"417.925", "m":"417,925", "f":2},"315730":{"n":"Santa Bárbara do Tugúrio", "v":"194.564", "m":"194,564", "f":0},"315733":{"n":"Santa Cruz de Minas", "v":"3.565", "m":"3,565", "f":0},"315737":{"n":"Santa Cruz de Salinas", "v":"589.607", "m":"589,607", "f":2},"315740":{"n":"Santa Cruz do Escalvado", "v":"258.726", "m":"258,726", "f":1},"315750":{"n":"Santa Efigênia de Minas", "v":"131.965", "m":"131,965", "f":0},"315760":{"n":"Santa Fé de Minas", "v":"2917.448", "m":"2.917,448", "f":3},"315765":{"n":"Santa Helena de Minas", "v":"276.433", "m":"276,433", "f":1},"315770":{"n":"Santa Juliana", "v":"723.784", "m":"723,784", "f":2},"315780":{"n":"Santa Luzia", "v":"235.327", "m":"235,327", "f":1},"315790":{"n":"Santa Margarida", "v":"255.73", "m":"255,730", "f":1},"315800":{"n":"Santa Maria de Itabira", "v":"597.437", "m":"597,437", "f":2},"315810":{"n":"Santa Maria do Salto", "v":"440.605", "m":"440,605", "f":2},"315820":{"n":"Santa Maria do Suaçuí", "v":"624.047", "m":"624,047", "f":2},"315830":{"n":"Santana da Vargem", "v":"172.444", "m":"172,444", "f":0},"315840":{"n":"Santana de Cataguases", "v":"161.486", "m":"161,486", "f":0},"315850":{"n":"Santana de Pirapama", "v":"1255.832", "m":"1.255,832", "f":3},"315860":{"n":"Santana do Deserto", "v":"182.655", "m":"182,655", "f":0},"315870":{"n":"Santana do Garambéu", "v":"203.074", "m":"203,074", "f":1},"315880":{"n":"Santana do Jacaré", "v":"106.169", "m":"106,169", "f":0},"315890":{"n":"Santana do Manhuaçu", "v":"347.362", "m":"347,362", "f":1},"315895":{"n":"Santana do Paraíso", "v":"276.067", "m":"276,067", "f":1},"315900":{"n":"Santana do Riacho", "v":"677.207", "m":"677,207", "f":2},"315910":{"n":"Santana dos Montes", "v":"196.565", "m":"196,565", "f":0},"315920":{"n":"Santa Rita de Caldas", "v":"503.011", "m":"503,011", "f":2},"315930":{"n":"Santa Rita de Jacutinga", "v":"420.94", "m":"420,940", "f":2},"315935":{"n":"Santa Rita de Minas", "v":"68.153", "m":"68,153", "f":0},"315940":{"n":"Santa Rita de Ibitipoca", "v":"324.234", "m":"324,234", "f":1},"315950":{"n":"Santa Rita do Itueto", "v":"485.081", "m":"485,081", "f":2},"315960":{"n":"Santa Rita do Sapucaí", "v":"352.969", "m":"352,969", "f":1},"315970":{"n":"Santa Rosa da Serra", "v":"284.334", "m":"284,334", "f":1},"315980":{"n":"Santa Vitória", "v":"3001.357", "m":"3.001,357", "f":3},"315990":{"n":"Santo Antônio do Amparo", "v":"488.885", "m":"488,885", "f":2},"316000":{"n":"Santo Antônio do Aventureiro", "v":"202.033", "m":"202,033", "f":1},"316010":{"n":"Santo Antônio do Grama", "v":"130.213", "m":"130,213", "f":0},"316020":{"n":"Santo Antônio do Itambé", "v":"305.737", "m":"305,737", "f":1},"316030":{"n":"Santo Antônio do Jacinto", "v":"503.376", "m":"503,376", "f":2},"316040":{"n":"Santo Antônio do Monte", "v":"1125.78", "m":"1.125,780", "f":3},"316045":{"n":"Santo Antônio do Retiro", "v":"796.29", "m":"796,290", "f":3},"316050":{"n":"Santo Antônio do Rio Abaixo", "v":"107.269", "m":"107,269", "f":0},"316060":{"n":"Santo Hipólito", "v":"430.656", "m":"430,656", "f":2},"316070":{"n":"Santos Dumont", "v":"637.373", "m":"637,373", "f":2},"316080":{"n":"São Bento Abade", "v":"80.403", "m":"80,403", "f":0},"316090":{"n":"São Brás do Suaçuí", "v":"110.019", "m":"110,019", "f":0},"316095":{"n":"São Domingos das Dores", "v":"60.865", "m":"60,865", "f":0},"316100":{"n":"São Domingos do Prata", "v":"743.768", "m":"743,768", "f":3},"316105":{"n":"São Félix de Minas", "v":"162.56", "m":"162,560", "f":0},"316110":{"n":"São Francisco", "v":"3308.1", "m":"3.308,100", "f":3},"316120":{"n":"São Francisco de Paula", "v":"316.822", "m":"316,822", "f":1},"316130":{"n":"São Francisco de Sales", "v":"1128.864", "m":"1.128,864", "f":3},"316140":{"n":"São Francisco do Glória", "v":"164.613", "m":"164,613", "f":0},"316150":{"n":"São Geraldo", "v":"185.578", "m":"185,578", "f":0},"316160":{"n":"São Geraldo da Piedade", "v":"152.336", "m":"152,336", "f":0},"316165":{"n":"São Geraldo do Baixio", "v":"280.954", "m":"280,954", "f":1},"316170":{"n":"São Gonçalo do Abaeté", "v":"2692.171", "m":"2.692,171", "f":3},"316180":{"n":"São Gonçalo do Pará", "v":"265.73", "m":"265,730", "f":1},"316190":{"n":"São Gonçalo do Rio Abaixo", "v":"363.828", "m":"363,828", "f":1},"316200":{"n":"São Gonçalo do Sapucaí", "v":"516.683", "m":"516,683", "f":2},"316210":{"n":"São Gotardo", "v":"866.087", "m":"866,087", "f":3},"316220":{"n":"São João Batista do Glória", "v":"547.908", "m":"547,908", "f":2},"316225":{"n":"São João da Lagoa", "v":"998.015", "m":"998,015", "f":3},"316230":{"n":"São João da Mata", "v":"120.536", "m":"120,536", "f":0},"316240":{"n":"São João da Ponte", "v":"1851.102", "m":"1.851,102", "f":3},"316245":{"n":"São João das Missões", "v":"678.274", "m":"678,274", "f":2},"316250":{"n":"São João del Rei", "v":"1451.64", "m":"1.451,640", "f":3},"316255":{"n":"São João do Manhuaçu", "v":"143.096", "m":"143,096", "f":0},"316257":{"n":"São João do Manteninha", "v":"137.928", "m":"137,928", "f":0},"316260":{"n":"São João do Oriente", "v":"120.122", "m":"120,122", "f":0},"316265":{"n":"São João do Pacuí", "v":"415.922", "m":"415,922", "f":2},"316270":{"n":"São João do Paraíso", "v":"1925.575", "m":"1.925,575", "f":3},"316280":{"n":"São João Evangelista", "v":"478.183", "m":"478,183", "f":2},"316290":{"n":"São João Nepomuceno", "v":"407.427", "m":"407,427", "f":2},"316292":{"n":"São Joaquim de Bicas", "v":"71.557", "m":"71,557", "f":0},"316294":{"n":"São José da Barra", "v":"314.253", "m":"314,253", "f":1},"316295":{"n":"São José da Lapa", "v":"47.93", "m":"47,930", "f":0},"316300":{"n":"São José da Safira", "v":"213.881", "m":"213,881", "f":1},"316310":{"n":"São José da Varginha", "v":"205.501", "m":"205,501", "f":1},"316320":{"n":"São José do Alegre", "v":"88.794", "m":"88,794", "f":0},"316330":{"n":"São José do Divino", "v":"328.704", "m":"328,704", "f":1},"316340":{"n":"São José do Goiabal", "v":"184.511", "m":"184,511", "f":0},"316350":{"n":"São José do Jacuri", "v":"345.146", "m":"345,146", "f":1},"316360":{"n":"São José do Mantimento", "v":"54.701", "m":"54,701", "f":0},"316370":{"n":"São Lourenço", "v":"58.019", "m":"58,019", "f":0},"316380":{"n":"São Miguel do Anta", "v":"152.111", "m":"152,111", "f":0},"316390":{"n":"São Pedro da União", "v":"260.827", "m":"260,827", "f":1},"316400":{"n":"São Pedro dos Ferros", "v":"402.739", "m":"402,739", "f":2},"316410":{"n":"São Pedro do Suaçuí", "v":"308.106", "m":"308,106", "f":1},"316420":{"n":"São Romão", "v":"2434.004", "m":"2.434,004", "f":3},"316430":{"n":"São Roque de Minas", "v":"2098.867", "m":"2.098,867", "f":3},"316440":{"n":"São Sebastião da Bela Vista", "v":"167.157", "m":"167,157", "f":0},"316443":{"n":"São Sebastião da Vargem  Alegre", "v":"73.629", "m":"73,629", "f":0},"316447":{"n":"São Sebastião do Anta", "v":"80.618", "m":"80,618", "f":0},"316450":{"n":"São Sebastião do Maranhão", "v":"517.83", "m":"517,830", "f":2},"316460":{"n":"São Sebastião do Oeste", "v":"408.09", "m":"408,090", "f":2},"316470":{"n":"São Sebastião do Paraíso", "v":"814.925", "m":"814,925", "f":3},"316480":{"n":"São Sebastião do Rio Preto", "v":"128.002", "m":"128,002", "f":0},"316490":{"n":"São Sebastião do Rio Verde", "v":"90.848", "m":"90,848", "f":0},"316500":{"n":"São Tiago", "v":"572.4", "m":"572,400", "f":2},"316510":{"n":"São Tomás de Aquino", "v":"277.928", "m":"277,928", "f":1},"316520":{"n":"São Thomé das Letras", "v":"369.747", "m":"369,747", "f":2},"316530":{"n":"São Vicente de Minas", "v":"392.651", "m":"392,651", "f":2},"316540":{"n":"Sapucaí-Mirim", "v":"285.073", "m":"285,073", "f":1},"316550":{"n":"Sardoá", "v":"141.904", "m":"141,904", "f":0},"316553":{"n":"Sarzedo", "v":"62.134", "m":"62,134", "f":0},"316555":{"n":"Setubinha", "v":"534.655", "m":"534,655", "f":2},"316556":{"n":"Sem-Peixe", "v":"176.634", "m":"176,634", "f":0},"316557":{"n":"Senador Amaral", "v":"151.097", "m":"151,097", "f":0},"316560":{"n":"Senador Cortes", "v":"98.336", "m":"98,336", "f":0},"316570":{"n":"Senador Firmino", "v":"166.495", "m":"166,495", "f":0},"316580":{"n":"Senador José Bento", "v":"93.892", "m":"93,892", "f":0},"316590":{"n":"Senador Modestino Gonçalves", "v":"952.055", "m":"952,055", "f":3},"316600":{"n":"Senhora de Oliveira", "v":"170.749", "m":"170,749", "f":0},"316610":{"n":"Senhora do Porto", "v":"381.328", "m":"381,328", "f":2},"316620":{"n":"Senhora dos Remédios", "v":"237.815", "m":"237,815", "f":1},"316630":{"n":"Sericita", "v":"166.012", "m":"166,012", "f":0},"316640":{"n":"Seritinga", "v":"114.769", "m":"114,769", "f":0},"316650":{"n":"Serra Azul de Minas", "v":"218.595", "m":"218,595", "f":1},"316660":{"n":"Serra da Saudade", "v":"335.659", "m":"335,659", "f":1},"316670":{"n":"Serra dos Aimorés", "v":"213.561", "m":"213,561", "f":1},"316680":{"n":"Serra do Salitre", "v":"1295.272", "m":"1.295,272", "f":3},"316690":{"n":"Serrania", "v":"209.27", "m":"209,270", "f":1},"316695":{"n":"Serranópolis de Minas", "v":"551.954", "m":"551,954", "f":2},"316700":{"n":"Serranos", "v":"213.173", "m":"213,173", "f":1},"316710":{"n":"Serro", "v":"1217.813", "m":"1.217,813", "f":3},"316720":{"n":"Sete Lagoas", "v":"537.639", "m":"537,639", "f":2},"316730":{"n":"Silveirânia", "v":"157.456", "m":"157,456", "f":0},"316740":{"n":"Silvianópolis", "v":"312.166", "m":"312,166", "f":1},"316750":{"n":"Simão Pereira", "v":"135.689", "m":"135,689", "f":0},"316760":{"n":"Simonésia", "v":"486.543", "m":"486,543", "f":2},"316770":{"n":"Sobrália", "v":"206.787", "m":"206,787", "f":1},"316780":{"n":"Soledade de Minas", "v":"196.866", "m":"196,866", "f":1},"316790":{"n":"Tabuleiro", "v":"211.084", "m":"211,084", "f":1},"316800":{"n":"Taiobeiras", "v":"1220.023", "m":"1.220,023", "f":3},"316805":{"n":"Taparuba", "v":"193.082", "m":"193,082", "f":0},"316810":{"n":"Tapira", "v":"1179.248", "m":"1.179,248", "f":3},"316820":{"n":"Tapiraí", "v":"407.92", "m":"407,920", "f":2},"316830":{"n":"Taquaraçu de Minas", "v":"329.241", "m":"329,241", "f":1},"316840":{"n":"Tarumirim", "v":"731.753", "m":"731,753", "f":3},"316850":{"n":"Teixeiras", "v":"166.735", "m":"166,735", "f":0},"316860":{"n":"Teófilo Otoni", "v":"3242.27", "m":"3.242,270", "f":3},"316870":{"n":"Timóteo", "v":"144.381", "m":"144,381", "f":0},"316880":{"n":"Tiradentes", "v":"83.047", "m":"83,047", "f":0},"316890":{"n":"Tiros", "v":"2091.774", "m":"2.091,774", "f":3},"316900":{"n":"Tocantins", "v":"173.866", "m":"173,866", "f":0},"316905":{"n":"Tocos do Moji", "v":"114.705", "m":"114,705", "f":0},"316910":{"n":"Toledo", "v":"136.776", "m":"136,776", "f":0},"316920":{"n":"Tombos", "v":"285.125", "m":"285,125", "f":1},"316930":{"n":"Três Corações", "v":"828.038", "m":"828,038", "f":3},"316935":{"n":"Três Marias", "v":"2678.253", "m":"2.678,253", "f":3},"316940":{"n":"Três Pontas", "v":"689.794", "m":"689,794", "f":2},"316950":{"n":"Tumiritinga", "v":"500.073", "m":"500,073", "f":2},"316960":{"n":"Tupaciguara", "v":"1823.96", "m":"1.823,960", "f":3},"316970":{"n":"Turmalina", "v":"1153.111", "m":"1.153,111", "f":3},"316980":{"n":"Turvolândia", "v":"221", "m":"221,000", "f":1},"316990":{"n":"Ubá", "v":"407.452", "m":"407,452", "f":2},"317000":{"n":"Ubaí", "v":"820.524", "m":"820,524", "f":3},"317005":{"n":"Ubaporanga", "v":"189.045", "m":"189,045", "f":0},"317010":{"n":"Uberaba", "v":"4523.957", "m":"4.523,957", "f":3},"317020":{"n":"Uberlândia", "v":"4115.206", "m":"4.115,206", "f":3},"317030":{"n":"Umburatiba", "v":"405.834", "m":"405,834", "f":2},"317040":{"n":"Unaí", "v":"8447.417", "m":"8.447,417", "f":3},"317043":{"n":"União de Minas", "v":"1147.407", "m":"1.147,407", "f":3},"317047":{"n":"Uruana de Minas", "v":"598.072", "m":"598,072", "f":2},"317050":{"n":"Urucânia", "v":"138.792", "m":"138,792", "f":0},"317052":{"n":"Urucuia", "v":"2076.942", "m":"2.076,942", "f":3},"317057":{"n":"Vargem Alegre", "v":"116.664", "m":"116,664", "f":0},"317060":{"n":"Vargem Bonita", "v":"409.888", "m":"409,888", "f":2},"317065":{"n":"Vargem Grande do Rio Pardo", "v":"491.512", "m":"491,512", "f":2},"317070":{"n":"Varginha", "v":"395.396", "m":"395,396", "f":2},"317075":{"n":"Varjão de Minas", "v":"651.556", "m":"651,556", "f":2},"317080":{"n":"Várzea da Palma", "v":"2220.279", "m":"2.220,279", "f":3},"317090":{"n":"Varzelândia", "v":"814.994", "m":"814,994", "f":3},"317100":{"n":"Vazante", "v":"1913.396", "m":"1.913,396", "f":3},"317103":{"n":"Verdelândia", "v":"1570.577", "m":"1.570,577", "f":3},"317107":{"n":"Veredinha", "v":"631.692", "m":"631,692", "f":2},"317110":{"n":"Veríssimo", "v":"1031.823", "m":"1.031,823", "f":3},"317115":{"n":"Vermelho Novo", "v":"115.242", "m":"115,242", "f":0},"317120":{"n":"Vespasiano", "v":"71.222", "m":"71,222", "f":0},"317130":{"n":"Viçosa", "v":"299.418", "m":"299,418", "f":1},"317140":{"n":"Vieiras", "v":"112.691", "m":"112,691", "f":0},"317150":{"n":"Mathias Lobato", "v":"172.302", "m":"172,302", "f":0},"317160":{"n":"Virgem da Lapa", "v":"868.914", "m":"868,914", "f":3},"317170":{"n":"Virgínia", "v":"326.515", "m":"326,515", "f":1},"317180":{"n":"Virginópolis", "v":"439.878", "m":"439,878", "f":2},"317190":{"n":"Virgolândia", "v":"281.022", "m":"281,022", "f":1},"317200":{"n":"Visconde do Rio Branco", "v":"243.351", "m":"243,351", "f":1},"317210":{"n":"Volta Grande", "v":"205.552", "m":"205,552", "f":1},"317220":{"n":"Wenceslau Braz", "v":"102.487", "m":"102,487", "f":0}},"filtro":[[3.565,196.565],[196.735,363.828],[365.923,727.894],[731.753,10727.471]]}